[
    {
        "title": "Orion and the Dark",
        "imdb_id": "tt28066777",
        "poster_url": null
    },
    {
        "title": "Anne at 13,000 Ft.",
        "imdb_id": "tt10874006",
        "poster_url": null
    },
    {
        "title": "Jack Whitehall: Settle Down",
        "imdb_id": "tt30460532",
        "poster_url": null
    },
    {
        "title": "Fallen Leaves",
        "imdb_id": "tt21027780",
        "poster_url": null
    },
    {
        "title": "It Is Night in America",
        "imdb_id": "tt21228958",
        "poster_url": null
    },
    {
        "title": "The Reason I Jump",
        "imdb_id": "tt9098928",
        "poster_url": null
    },
    {
        "title": "The Greatest Night in Pop",
        "imdb_id": "tt30796448",
        "poster_url": null
    },
    {
        "title": "Bruiser",
        "imdb_id": "tt21833464",
        "poster_url": null
    },
    {
        "title": "In the Morning of La Petite Mort",
        "imdb_id": "tt15435040",
        "poster_url": null
    },
    {
        "title": "Prime",
        "imdb_id": "tt28356390",
        "poster_url": null
    }
]