[
    {
        "title": "You Are Not Alone: Fighting the Wolf Pack",
        "imdb_id": "tt31410930",
        "poster_url": null
    },
    {
        "title": "Through the Olive Trees",
        "imdb_id": "tt0111845",
        "poster_url": null
    },
    {
        "title": "The Pig, the Snake and the Pigeon",
        "imdb_id": "tt29319990",
        "poster_url": null
    },
    {
        "title": "Career Girls",
        "imdb_id": "tt0118818",
        "poster_url": null
    },
    {
        "title": "Code 8 Part II",
        "imdb_id": "tt14764464",
        "poster_url": null
    },
    {
        "title": "TINA",
        "imdb_id": "tt8399720",
        "poster_url": null
    },
    {
        "title": "Kids Are Growing Up: A Story About a Kid Named Laroi",
        "imdb_id": "tt31415596",
        "poster_url": null
    },
    {
        "title": "The Twentieth Century",
        "imdb_id": "tt7969836",
        "poster_url": null
    },
    {
        "title": "ManSuang",
        "imdb_id": "tt28686328",
        "poster_url": null
    },
    {
        "title": "Spaceman",
        "imdb_id": "tt11097384",
        "poster_url": null
    }
]