[
    {
        "title": "The Vertical Ray of the Sun",
        "imdb_id": "tt0224578",
        "poster_url": null
    },
    {
        "title": "The Promised Land",
        "imdb_id": "tt20561198",
        "poster_url": null
    },
    {
        "title": "Fancy Dance",
        "imdb_id": "tt21813994",
        "poster_url": null
    },
    {
        "title": "Mario",
        "imdb_id": "tt6999052",
        "poster_url": null
    },
    {
        "title": "A Family Affair",
        "imdb_id": "tt21051906",
        "poster_url": null
    },
    {
        "title": "Jab We Met",
        "imdb_id": "tt1093370",
        "poster_url": null
    },
    {
        "title": "Tokyo Fist",
        "imdb_id": "tt0114690",
        "poster_url": null
    },
    {
        "title": "Stranger by the Lake",
        "imdb_id": "tt2852458",
        "poster_url": null
    },
    {
        "title": "Nicholas Nickleby",
        "imdb_id": "tt0309912",
        "poster_url": null
    },
    {
        "title": "Tabu",
        "imdb_id": "tt2153963",
        "poster_url": null
    }
]