[
    {
        "title": "The Missing Picture",
        "imdb_id": "tt2852470",
        "poster_url": null
    },
    {
        "title": "Leviathan",
        "imdb_id": "tt2802154",
        "poster_url": null
    },
    {
        "title": "In the Soup",
        "imdb_id": "tt0104503",
        "poster_url": null
    },
    {
        "title": "The Imaginary",
        "imdb_id": "tt16369708",
        "poster_url": null
    },
    {
        "title": "Space Cadet",
        "imdb_id": "tt21469794",
        "poster_url": null
    },
    {
        "title": "Pushing Hands",
        "imdb_id": "tt0105652",
        "poster_url": null
    },
    {
        "title": "Mansfield Park",
        "imdb_id": "tt0178737",
        "poster_url": null
    },
    {
        "title": "Ultraman: Rising",
        "imdb_id": "tt9471678",
        "poster_url": null
    },
    {
        "title": "Chicken for Linda!",
        "imdb_id": "tt21042126",
        "poster_url": null
    },
    {
        "title": "The Emperor and the Assassin",
        "imdb_id": "tt0162866",
        "poster_url": null
    }
]